niquery/__init__.py
niquery/__main__.py
niquery/_version.py
niquery/py.typed
niquery/analysis/__init__.py
niquery/analysis/featuring.py
niquery/analysis/filtering.py
niquery/cli/__init__.py
niquery/cli/run.py
niquery/cli/utils.py
niquery/data/__init__.py
niquery/data/fetching.py
niquery/data/remotes.py
niquery/data/utils.py
niquery/io/__init__.py
niquery/io/utils.py
niquery/query/__init__.py
niquery/query/querying.py
niquery/utils/__init__.py
niquery/utils/attributes.py
niquery/utils/decorators.py
niquery/utils/logging.py
niquery/utils/optpckg.py
niquery-25.0.0rc2.dist-info/METADATA
niquery-25.0.0rc2.dist-info/WHEEL
niquery-25.0.0rc2.dist-info/entry_points.txt
niquery-25.0.0rc2.dist-info/licenses/LICENSE
niquery-25.0.0rc2.dist-info/RECORD
