Metadata-Version: 2.4
Name: niquery
Version: 25.0.0rc2
Summary: OpenNeuro dataset query and characterization tool
Project-URL: Documentation, https://www.nipreps.org/niquery
Project-URL: Repository, https://github.com/nipreps/niquery.git
Project-URL: NiPreps, https://www.nipreps.org/
Author-email: The NiPreps Developers <nipreps@gmail.com>
Maintainer-email: The NiPreps Developers <nipreps@gmail.com>
License-Expression: Apache-2.0
License-File: LICENSE
Keywords: BIDS,OpenNeuro,data sharing,neuroimaging,web querying
Classifier: Development Status :: 3 - Alpha
Classifier: Intended Audience :: Science/Research
Classifier: Programming Language :: Python
Classifier: Topic :: Scientific/Engineering :: Image Recognition
Requires-Python: >=3.10
Requires-Dist: boto3
Requires-Dist: botocore
Requires-Dist: click
Requires-Dist: datalad
Requires-Dist: nibabel
Requires-Dist: pandas
Requires-Dist: requests
Requires-Dist: tqdm
Provides-Extra: all
Requires-Dist: attrs>=20.1.0; extra == 'all'
Requires-Dist: coverage; extra == 'all'
Requires-Dist: furo>=2024.01.29; extra == 'all'
Requires-Dist: nbsphinx; extra == 'all'
Requires-Dist: packaging; extra == 'all'
Requires-Dist: pandas-stubs; extra == 'all'
Requires-Dist: pre-commit; extra == 'all'
Requires-Dist: pre-commit-hooks; extra == 'all'
Requires-Dist: pydot>=1.2.3; extra == 'all'
Requires-Dist: pydotplus; extra == 'all'
Requires-Dist: pytest; extra == 'all'
Requires-Dist: pytest-cov; extra == 'all'
Requires-Dist: pytest-env; extra == 'all'
Requires-Dist: pytest-xdist>=1.28; extra == 'all'
Requires-Dist: pytest>=4.4; extra == 'all'
Requires-Dist: ruff; extra == 'all'
Requires-Dist: sphinx; extra == 'all'
Requires-Dist: sphinx-argparse; extra == 'all'
Requires-Dist: sphinx-click; extra == 'all'
Requires-Dist: sphinx-rtd-theme; extra == 'all'
Requires-Dist: sphinxcontrib-apidoc; extra == 'all'
Requires-Dist: sphinxcontrib-bibtex; extra == 'all'
Requires-Dist: sphinxcontrib-napoleon; extra == 'all'
Requires-Dist: sphinxcontrib-versioning; extra == 'all'
Requires-Dist: types-attrs; extra == 'all'
Requires-Dist: types-setuptools; extra == 'all'
Requires-Dist: types-tqdm; extra == 'all'
Provides-Extra: dev
Requires-Dist: pre-commit; extra == 'dev'
Requires-Dist: pre-commit-hooks; extra == 'dev'
Requires-Dist: ruff; extra == 'dev'
Provides-Extra: doc
Requires-Dist: attrs>=20.1.0; extra == 'doc'
Requires-Dist: furo>=2024.01.29; extra == 'doc'
Requires-Dist: nbsphinx; extra == 'doc'
Requires-Dist: packaging; extra == 'doc'
Requires-Dist: pydot>=1.2.3; extra == 'doc'
Requires-Dist: pydotplus; extra == 'doc'
Requires-Dist: sphinx; extra == 'doc'
Requires-Dist: sphinx-argparse; extra == 'doc'
Requires-Dist: sphinx-click; extra == 'doc'
Requires-Dist: sphinx-rtd-theme; extra == 'doc'
Requires-Dist: sphinxcontrib-apidoc; extra == 'doc'
Requires-Dist: sphinxcontrib-bibtex; extra == 'doc'
Requires-Dist: sphinxcontrib-napoleon; extra == 'doc'
Requires-Dist: sphinxcontrib-versioning; extra == 'doc'
Provides-Extra: docs
Requires-Dist: attrs>=20.1.0; extra == 'docs'
Requires-Dist: furo>=2024.01.29; extra == 'docs'
Requires-Dist: nbsphinx; extra == 'docs'
Requires-Dist: packaging; extra == 'docs'
Requires-Dist: pydot>=1.2.3; extra == 'docs'
Requires-Dist: pydotplus; extra == 'docs'
Requires-Dist: sphinx; extra == 'docs'
Requires-Dist: sphinx-argparse; extra == 'docs'
Requires-Dist: sphinx-click; extra == 'docs'
Requires-Dist: sphinx-rtd-theme; extra == 'docs'
Requires-Dist: sphinxcontrib-apidoc; extra == 'docs'
Requires-Dist: sphinxcontrib-bibtex; extra == 'docs'
Requires-Dist: sphinxcontrib-napoleon; extra == 'docs'
Requires-Dist: sphinxcontrib-versioning; extra == 'docs'
Provides-Extra: test
Requires-Dist: coverage; extra == 'test'
Requires-Dist: pytest-cov; extra == 'test'
Requires-Dist: pytest-env; extra == 'test'
Requires-Dist: pytest-xdist>=1.28; extra == 'test'
Requires-Dist: pytest>=4.4; extra == 'test'
Provides-Extra: tests
Requires-Dist: coverage; extra == 'tests'
Requires-Dist: pytest-cov; extra == 'tests'
Requires-Dist: pytest-env; extra == 'tests'
Requires-Dist: pytest-xdist>=1.28; extra == 'tests'
Requires-Dist: pytest>=4.4; extra == 'tests'
Provides-Extra: types
Requires-Dist: pandas-stubs; extra == 'types'
Requires-Dist: pytest; extra == 'types'
Requires-Dist: types-attrs; extra == 'types'
Requires-Dist: types-setuptools; extra == 'types'
Requires-Dist: types-tqdm; extra == 'types'
